seu3d_tool/__init__.py
seu3d_tool/config_colormap.py
seu3d_tool/config_template.yaml
seu3d_tool/server.py
seu3d_tool/seu3d_config.yaml
seu3d_tool/assets/clientside_functions.js
seu3d_tool/assets/stylesheet.css
seu3d_tool/pages/STinteV.code-workspace
seu3d_tool/pages/spatial.py
seu3d_tool-0.1.6.dist-info/LICENSE
seu3d_tool-0.1.6.dist-info/METADATA
seu3d_tool-0.1.6.dist-info/WHEEL
seu3d_tool-0.1.6.dist-info/entry_points.txt
seu3d_tool-0.1.6.dist-info/top_level.txt
seu3d_tool-0.1.6.dist-info/RECORD
