Metadata-Version: 2.1
Name: seu3d-tool
Version: 0.1.6
Summary: A web server for visualization of spatial-temporal single cell transcriptomics data
Home-page: https://github.com/RainyBlue-w/STOmics-3D
Author: wuc
Author-email: 1078497976@qq.com
License: GNU GPLv3
Keywords: python single cell transcriptomics 3D visualization spatial temporal
License-File: LICENSE
Requires-Dist: dash==2.16.1
Requires-Dist: dash-bootstrap-components
Requires-Dist: dash-extensions==1.0.14
Requires-Dist: dash-iconify==0.1.2
Requires-Dist: dash-mantine-components==0.12.1
Requires-Dist: feffery-antd-components==0.2.11
Requires-Dist: feffery-utils-components==0.1.29
Requires-Dist: plotly
Requires-Dist: scanpy
Requires-Dist: squidpy
Requires-Dist: typing
Requires-Dist: typing_extensions
Requires-Dist: diskcache
Requires-Dist: fastapi
Requires-Dist: uvicorn
Requires-Dist: multiprocess
Requires-Dist: ruamel.yaml==0.18.6
